cellxgene_lamin_validator/__init__.py
cellxgene_lamin_validator/_curate.py
cellxgene_lamin_validator/_fields.py
cellxgene_lamin_validator/_validator.py
cellxgene_lamin_validator/datasets.py
cellxgene_lamin_validator-0.3.2.dist-info/LICENSE
cellxgene_lamin_validator-0.3.2.dist-info/WHEEL
cellxgene_lamin_validator-0.3.2.dist-info/METADATA
cellxgene_lamin_validator-0.3.2.dist-info/RECORD
