Metadata-Version: 2.1
Name: cellxgene_lamin_validator
Version: 0.3.2
Summary: Lamin validator for CELLxGENE schema.
Author-email: Lamin Labs <open-source@lamin.ai>
Requires-Dist: lamin-validator
Requires-Dist: pre-commit ; extra == "dev"
Requires-Dist: nox ; extra == "dev"
Requires-Dist: pytest>=6.0 ; extra == "dev"
Requires-Dist: pytest-cov ; extra == "dev"
Requires-Dist: nbproject_test ; extra == "dev"
Requires-Dist: cellxgene-schema ; extra == "dev"
Project-URL: Home, https://github.com/laminlabs/cellxgene-lamin-validator
Provides-Extra: dev
